{
  "data": [
    {
      "uid": "56d60e",
      "name": "Col1",
      "type": "histogram",
      "xsrc": "AlineLerner:56:e6b1ed",
      "x": [
        "0.5",
        "0.333333",
        "0.333333",
        "0.666667",
        "0.333333",
        "0.4",
        "0.333333",
        "1",
        "1",
        "0.5",
        "0.333333",
        "0.5",
        "0.5",
        "0.166667",
        "0.2",
        "0.833333",
        "0.5",
        "0.5",
        "1",
        "0.57143",
        "0.571428",
        "1",
        "0.6",
        "0.666667",
        "0.666667",
        "1",
        "1",
        "0.666667",
        "0.5",
        "0.5",
        "1",
        "0.666667",
        "0.333333",
        "0.5",
        "0.5",
        "0.333333",
        "0.5",
        "0.6",
        "0",
        "1",
        "0.4",
        "0.857143",
        "0.714286",
        "0.333333",
        "1",
        "0",
        "0.5",
        "0.4",
        "0.666667",
        "0.6666666",
        "0",
        "1",
        "1",
        "0",
        "0.666667",
        "1",
        "0.5",
        "0",
        "0.5",
        "0.2",
        "0.666666",
        "0.666667",
        "0",
        "0.75",
        "0.666667",
        "0",
        "1",
        "0",
        "0.333333",
        "0.428571",
        "0.857143",
        "0.666666",
        "0.5",
        "0.666667",
        "0.666667",
        "0",
        "0",
        "0",
        "0.5",
        "0.2",
        "0.666667",
        "0",
        "0.33333",
        "0.333333",
        "0.5",
        "0.75",
        "0.8",
        "1",
        "1",
        "0.5",
        "0.5",
        "0.666667",
        "0.666667",
        "1",
        "0.4",
        "0.66666",
        "0.4",
        "0",
        "0.141414",
        "0",
        "0",
        "1",
        "0.333333",
        "1",
        "1",
        "0"
      ],
      "xbins": {
        "end": 1.0499999999999998,
        "size": 0.1,
        "start": -0.05
      },
      "marker": {
        "line": {
          "color": "rgba(214, 39, 40, 0)"
        },
        "color": "rgb(39, 78, 19)"
      }
    }
  ],
  "layout": {
    "title": "Overall\u00a0Engineer Accuracy (n=106)",
    "width": 1116,
    "xaxis": {
      "type": "linear",
      "range": [
        -0.04999999999999993,
        1.0499999999999998
      ],
      "title": "Accuracy",
      "domain": [],
      "autorange": true
    },
    "yaxis": {
      "type": "linear",
      "range": [
        0,
        20
      ],
      "title": "Frequency",
      "domain": [],
      "autorange": true
    },
    "bargap": 0.14,
    "height": 587,
    "margin": {},
    "autosize": true,
    "showlegend": false
  }
}